AUTHORS.rst
CONTRIBUTING.rst
HISTORY.rst
LICENSE
MANIFEST.in
README.rst
setup.cfg
setup.py
docs/Makefile
docs/authors.rst
docs/conf.py
docs/contributing.rst
docs/history.rst
docs/index.rst
docs/installation.rst
docs/make.bat
docs/readme.rst
docs/usage.rst
redis_connector/__init__.py
redis_connector/constants.py
redis_connector/exceptions.py
redis_connector/redis_connector.py
redis_connector.egg-info/PKG-INFO
redis_connector.egg-info/SOURCES.txt
redis_connector.egg-info/dependency_links.txt
redis_connector.egg-info/not-zip-safe
redis_connector.egg-info/requires.txt
redis_connector.egg-info/top_level.txt
tests/test_redis_connector.py