Metadata-Version: 1.1
Name: redis-connector
Version: 0.0.3
Summary: Redis pub/sub connector
Home-page: https://github.com/monobot/redis_connector
Author: Héctor Alvarez (monobot)
Author-email: monobot.soft@gmail.com
License: Apache Software License 2.0
Keywords: redis_connector
Platform: UNKNOWN
Classifier: Development Status :: 2 - Pre-Alpha
Classifier: Intended Audience :: Developers
Classifier: License :: OSI Approved :: Apache Software License
Classifier: Natural Language :: English
Classifier: Programming Language :: Python :: 3.5
Classifier: Programming Language :: Python :: 3.6
